Metadata-Version: 1.0
Name: distributions-AndreiNutas
Version: 0.1.3
Summary: Gaussian and binomial distributions
Home-page: UNKNOWN
Author: Andrei Nutas
Author-email: UNKNOWN
License: UNKNOWN
Platform: UNKNOWN
